proyecto_1_transmisor__diseno/src/design/codification.sv
module codification (
    input logic [3:0] i,
    output logic [6:0] h
);

    logic [2:0] c;

    assign c[0] = i[0] ^ i[1] ^ i[3];
    assign c[1] = i[0] ^ i[2] ^ i[3];
    assign c[2] = i[1] ^ i[2] ^ i[3];

    assign h = {i[3], i[2], i[1], c[2], i[0], c[1], c[0]};


    
endmodule

proyecto_1_transmisor__diseno/src/sim/codification_tb.sv
`timescale 1ns/1ps

module codification_tb;

    // Señales de prueba
    logic [3:0] i;
    logic [6:0] h;

    // Instancia del DUT (Device Under Test)
    codification dut (
        .i(i),
        .h(h)
    );

    // Proceso de estímulos
    initial begin
        $display(" i    |    h ");
        $display("--------------");

        // Probar todas las combinaciones (0 a 15)
        for (int k = 0; k < 16; k++) begin
            i = k;
            #10; // esperar 10 ns
            $display("%b  |  %b", i, h);
        end

        $finish;
    end

    initial begin
        $dumpfile("codification_tb.vcd");  // For waveform viewing
        $dumpvars(0, codification_tb);
    end

endmodule

proyecto_1_transmisor__diseno/src/build/codification_tb.vcd
$date
	Tue Apr 07 00:17:00 2026
$end
$version
	Icarus Verilog
$end
$timescale
	1ps
$end
$scope module codification_tb $end
$var wire 7 ! h [6:0] $end
$var reg 4 " i [3:0] $end
$scope module dut $end
$var wire 4 # i [3:0] $end
$var wire 7 $ h [6:0] $end
$var wire 3 % c [2:0] $end
$upscope $end
$scope begin $ivl_for_loop0 $end
$var integer 32 & k [31:0] $end
$upscope $end
$upscope $end
$enddefinitions $end
$comment Show the parameter values. $end
$dumpall
$end
#0
$dumpvars
b0 &
b0 %
b0 $
b0 #
b0 "
b0 !
$end
#10000
b11 %
b111 !
b111 $
b1 "
b1 #
b1 &
#20000
b101 %
b11001 !
b11001 $
b10 "
b10 #
b10 &
#30000
b110 %
b11110 !
b11110 $
b11 "
b11 #
b11 &
#40000
b101010 !
b101010 $
b100 "
b100 #
b100 &
#50000
b101 %
b101101 !
b101101 $
b101 "
b101 #
b101 &
#60000
b11 %
b110011 !
b110011 $
b110 "
b110 #
b110 &
#70000
b0 %
b110100 !
b110100 $
b111 "
b111 #
b111 &
#80000
b111 %
b1001011 !
b1001011 $
b1000 "
b1000 #
b1000 &
#90000
b100 %
b1001100 !
b1001100 $
b1001 "
b1001 #
b1001 &
#100000
b10 %
b1010010 !
b1010010 $
b1010 "
b1010 #
b1010 &
#110000
b1 %
b1010101 !
b1010101 $
b1011 "
b1011 #
b1011 &
#120000
b1100001 !
b1100001 $
b1100 "
b1100 #
b1100 &
#130000
b10 %
b1100110 !
b1100110 $
b1101 "
b1101 #
b1101 &
#140000
b100 %
b1111000 !
b1111000 $
b1110 "
b1110 #
b1110 &
#150000
b111 %
b1111111 !
b1111111 $
b1111 "
b1111 #
b1111 &
#160000
b10000 &
