proyecto_1_transmisor__diseno/src/design/error_generator.sv
module error_generator (
    input logic [2:0] error_pos,
    input logic [6:0] datos,
    output logic [6:0] datos_error
);

    logic [6:0] mascara;

    assign mascara = (error_pos == 3'b000) ? 7'b0000000:  7'b0000001 << (error_pos-1);

    assign datos_error = datos ^ mascara;

endmodule

proyecto_1_transmisor__diseno/src/sim/error_generator_tb.sv
`timescale 1ns/1ps

module error_generator_tb;

    logic [2:0] error_pos;
    logic [6:0] datos;
    logic [6:0] datos_error;

    logic [6:0] expected;

    // DUT
    error_generator dut (
        .error_pos(error_pos),
        .datos(datos),
        .datos_error(datos_error)
    );

    // Modelo esperado
    always_comb begin
        if (error_pos == 3'b000)
            expected = datos;
        else
            expected = datos ^ (7'b1 << (error_pos - 1));
    end

    initial begin
        $display("INICIO TEST");

        // Probar TODOS los datos (7 bits) y todas las posiciones
        for (int d = 0; d < 128; d++) begin
            datos = d;

            for (int p = 0; p < 8; p++) begin
                error_pos = p;
                #5;

                if (datos_error !== expected) begin
                    $error("FALLO: datos=%b pos=%0d | salida=%b esperado=%b",
                            datos, error_pos, datos_error, expected);
                end
            end
        end

        $display("TEST COMPLETADO SIN ERRORES");
        $finish;
    end

    initial begin
        $dumpfile("error_generator_tb.vcd");  // For waveform viewing
        $dumpvars(0, error_generator_tb);
    end

endmodule

proyecto_1_transmisor__diseno/src/build/error_generator_tb.vcd
$date
	Tue Apr 07 01:29:00 2026
$end
$version
	Icarus Verilog
$end
$timescale
	1ps
$end
$scope module error_generator_tb $end
$var wire 7 ! datos_error [6:0] $end
$var reg 7 " datos [6:0] $end
$var reg 3 # error_pos [2:0] $end
$var reg 7 $ expected [6:0] $end
$scope module dut $end
$var wire 7 % datos [6:0] $end
$var wire 7 & datos_error [6:0] $end
$var wire 3 ' error_pos [2:0] $end
$var wire 7 ( mascara [6:0] $end
$upscope $end
$scope begin $ivl_for_loop0 $end
$var integer 32 ) d [31:0] $end
$scope begin $ivl_for_loop1 $end
$var integer 32 * p [31:0] $end
$upscope $end
$upscope $end
$upscope $end
$enddefinitions $end
$comment Show the parameter values. $end
$dumpall
$end
#0
$dumpvars
b0 *
b0 )
b0 (
b0 '
b0 &
b0 %
b0 $
b0 #
b0 "
b0 !
$end
#5000
b1 !
b1 &
b1 (
b1 $
b1 #
b1 '
b1 *
#10000
b10 !
b10 &
b10 (
b10 $
b10 #
b10 '
b10 *
#15000
b100 !
b100 &
b100 (
b100 $
b11 #
b11 '
b11 *
#20000
b1000 !
b1000 &
b1000 (
b1000 $
b100 #
b100 '
b100 *
#25000
b10000 !
b10000 &
b10000 (
b10000 $
b101 #
b101 '
b101 *
#30000
b100000 !
b100000 &
b100000 (
b100000 $
b110 #
b110 '
b110 *
#35000
b1000000 !
b1000000 &
b1000000 (
b1000000 $
b111 #
b111 '
b111 *
#40000
b0 (
b1 !
b1 &
b1 $
b0 #
b0 '
b1 "
b1 %
b1 )
b0 *
#45000
b0 !
b0 &
b1 (
b0 $
b1 #
b1 '
b1 *
#50000
b11 !
b11 &
b10 (
b11 $
b10 #
b10 '
b10 *
#55000
b101 !
b101 &
b100 (
b101 $
b11 #
b11 '
b11 *
#60000
b1001 !
b1001 &
b1000 (
b1001 $
b100 #
b100 '
b100 *
#65000
b10001 !
b10001 &
b10000 (
b10001 $
b101 #
b101 '
b101 *
#70000
b100001 !
b100001 &
b100000 (
b100001 $
b110 #
b110 '
b110 *
#75000
b1000001 !
b1000001 &
b1000000 (
b1000001 $
b111 #
b111 '
b111 *
#80000
b0 (
b10 !
b10 &
b10 $
b0 #
b0 '
b10 "
b10 %
b10 )
b0 *
#85000
b11 !
b11 &
b1 (
b11 $
b1 #
b1 '
b1 *
#90000
b0 !
b0 &
b10 (
b0 $
b10 #
b10 '
b10 *
#95000
b110 !
b110 &
b100 (
b110 $
b11 #
b11 '
b11 *
#100000
b1010 !
b1010 &
b1000 (
b1010 $
b100 #
b100 '
b100 *
#105000
b10010 !
b10010 &
b10000 (
b10010 $
b101 #
b101 '
b101 *
#110000
b100010 !
b100010 &
b100000 (
b100010 $
b110 #
b110 '
b110 *
#115000
b1000010 !
b1000010 &
b1000000 (
b1000010 $
b111 #
b111 '
b111 *
#120000
b0 (
b11 !
b11 &
b11 $
b0 #
b0 '
b11 "
b11 %
b11 )
b0 *
#125000
b10 !
b10 &
b1 (
b10 $
b1 #
b1 '
b1 *
#130000
b1 !
b1 &
b10 (
b1 $
b10 #
b10 '
b10 *
#135000
b111 !
b111 &
b100 (
b111 $
b11 #
b11 '
b11 *
#140000
b1011 !
b1011 &
b1000 (
b1011 $
b100 #
b100 '
b100 *
#145000
b10011 !
b10011 &
b10000 (
b10011 $
b101 #
b101 '
b101 *
#150000
b100011 !
b100011 &
b100000 (
b100011 $
b110 #
b110 '
b110 *
#155000
b1000011 !
b1000011 &
b1000000 (
b1000011 $
b111 #
b111 '
b111 *
#160000
b0 (
b100 !
b100 &
b100 $
b0 #
b0 '
b100 "
b100 %
b100 )
b0 *
#165000
b101 !
b101 &
b1 (
b101 $
b1 #
b1 '
b1 *
#170000
b110 !
b110 &
b10 (
b110 $
b10 #
b10 '
b10 *
#175000
b0 !
b0 &
b100 (
b0 $
b11 #
b11 '
b11 *
#180000
b1100 !
b1100 &
b1000 (
b1100 $
b100 #
b100 '
b100 *
#185000
b10100 !
b10100 &
b10000 (
b10100 $
b101 #
b101 '
b101 *
#190000
b100100 !
b100100 &
b100000 (
b100100 $
b110 #
b110 '
b110 *
#195000
b1000100 !
b1000100 &
b1000000 (
b1000100 $
b111 #
b111 '
b111 *
#200000
b0 (
b101 !
b101 &
b101 $
b0 #
b0 '
b101 "
b101 %
b101 )
b0 *
#205000
b100 !
b100 &
b1 (
b100 $
b1 #
b1 '
b1 *
#210000
b111 !
b111 &
b10 (
b111 $
b10 #
b10 '
b10 *
#215000
b1 !
b1 &
b100 (
b1 $
b11 #
b11 '
b11 *
#220000
b1101 !
b1101 &
b1000 (
b1101 $
b100 #
b100 '
b100 *
#225000
b10101 !
b10101 &
b10000 (
b10101 $
b101 #
b101 '
b101 *
#230000
b100101 !
b100101 &
b100000 (
b100101 $
b110 #
b110 '
b110 *
#235000
b1000101 !
b1000101 &
b1000000 (
b1000101 $
b111 #
b111 '
b111 *
#240000
b0 (
b110 !
b110 &
b110 $
b0 #
b0 '
b110 "
b110 %
b110 )
b0 *
#245000
b111 !
b111 &
b1 (
b111 $
b1 #
b1 '
b1 *
#250000
b100 !
b100 &
b10 (
b100 $
b10 #
b10 '
b10 *
#255000
b10 !
b10 &
b100 (
b10 $
b11 #
b11 '
b11 *
#260000
b1110 !
b1110 &
b1000 (
b1110 $
b100 #
b100 '
b100 *
#265000
b10110 !
b10110 &
b10000 (
b10110 $
b101 #
b101 '
b101 *
#270000
b100110 !
b100110 &
b100000 (
b100110 $
b110 #
b110 '
b110 *
#275000
b1000110 !
b1000110 &
b1000000 (
b1000110 $
b111 #
b111 '
b111 *
#280000
b0 (
b111 !
b111 &
b111 $
b0 #
b0 '
b111 "
b111 %
b111 )
b0 *
#285000
b110 !
b110 &
b1 (
b110 $
b1 #
b1 '
b1 *
#290000
b101 !
b101 &
b10 (
b101 $
b10 #
b10 '
b10 *
#295000
b11 !
b11 &
b100 (
b11 $
b11 #
b11 '
b11 *
#300000
b1111 !
b1111 &
b1000 (
b1111 $
b100 #
b100 '
b100 *
#305000
b10111 !
b10111 &
b10000 (
b10111 $
b101 #
b101 '
b101 *
#310000
b100111 !
b100111 &
b100000 (
b100111 $
b110 #
b110 '
b110 *
#315000
b1000111 !
b1000111 &
b1000000 (
b1000111 $
b111 #
b111 '
b111 *
#320000
b0 (
b1000 !
b1000 &
b1000 $
b0 #
b0 '
b1000 "
b1000 %
b1000 )
b0 *
#325000
b1001 !
b1001 &
b1 (
b1001 $
b1 #
b1 '
b1 *
#330000
b1010 !
b1010 &
b10 (
b1010 $
b10 #
b10 '
b10 *
#335000
b1100 !
b1100 &
b100 (
b1100 $
b11 #
b11 '
b11 *
#340000
b0 !
b0 &
b1000 (
b0 $
b100 #
b100 '
b100 *
#345000
b11000 !
b11000 &
b10000 (
b11000 $
b101 #
b101 '
b101 *
#350000
b101000 !
b101000 &
b100000 (
b101000 $
b110 #
b110 '
b110 *
#355000
b1001000 !
b1001000 &
b1000000 (
b1001000 $
b111 #
b111 '
b111 *
#360000
b0 (
b1001 !
b1001 &
b1001 $
b0 #
b0 '
b1001 "
b1001 %
b1001 )
b0 *
#365000
b1000 !
b1000 &
b1 (
b1000 $
b1 #
b1 '
b1 *
#370000
b1011 !
b1011 &
b10 (
b1011 $
b10 #
b10 '
b10 *
#375000
b1101 !
b1101 &
b100 (
b1101 $
b11 #
b11 '
b11 *
#380000
b1 !
b1 &
b1000 (
b1 $
b100 #
b100 '
b100 *
#385000
b11001 !
b11001 &
b10000 (
b11001 $
b101 #
b101 '
b101 *
#390000
b101001 !
b101001 &
b100000 (
b101001 $
b110 #
b110 '
b110 *
#395000
b1001001 !
b1001001 &
b1000000 (
b1001001 $
b111 #
b111 '
b111 *
#400000
b0 (
b1010 !
b1010 &
b1010 $
b0 #
b0 '
b1010 "
b1010 %
b1010 )
b0 *
#405000
b1011 !
b1011 &
b1 (
b1011 $
b1 #
b1 '
b1 *
#410000
b1000 !
b1000 &
b10 (
b1000 $
b10 #
b10 '
b10 *
#415000
b1110 !
b1110 &
b100 (
b1110 $
b11 #
b11 '
b11 *
#420000
b10 !
b10 &
b1000 (
b10 $
b100 #
b100 '
b100 *
#425000
b11010 !
b11010 &
b10000 (
b11010 $
b101 #
b101 '
b101 *
#430000
b101010 !
b101010 &
b100000 (
b101010 $
b110 #
b110 '
b110 *
#435000
b1001010 !
b1001010 &
b1000000 (
b1001010 $
b111 #
b111 '
b111 *
#440000
b0 (
b1011 !
b1011 &
b1011 $
b0 #
b0 '
b1011 "
b1011 %
b1011 )
b0 *
#445000
b1010 !
b1010 &
b1 (
b1010 $
b1 #
b1 '
b1 *
#450000
b1001 !
b1001 &
b10 (
b1001 $
b10 #
b10 '
b10 *
#455000
b1111 !
b1111 &
b100 (
b1111 $
b11 #
b11 '
b11 *
#460000
b11 !
b11 &
b1000 (
b11 $
b100 #
b100 '
b100 *
#465000
b11011 !
b11011 &
b10000 (
b11011 $
b101 #
b101 '
b101 *
#470000
b101011 !
b101011 &
b100000 (
b101011 $
b110 #
b110 '
b110 *
#475000
b1001011 !
b1001011 &
b1000000 (
b1001011 $
b111 #
b111 '
b111 *
#480000
b0 (
b1100 !
b1100 &
b1100 $
b0 #
b0 '
b1100 "
b1100 %
b1100 )
b0 *
#485000
b1101 !
b1101 &
b1 (
b1101 $
b1 #
b1 '
b1 *
#490000
b1110 !
b1110 &
b10 (
b1110 $
b10 #
b10 '
b10 *
#495000
b1000 !
b1000 &
b100 (
b1000 $
b11 #
b11 '
b11 *
#500000
b100 !
b100 &
b1000 (
b100 $
b100 #
b100 '
b100 *
#505000
b11100 !
b11100 &
b10000 (
b11100 $
b101 #
b101 '
b101 *
#510000
b101100 !
b101100 &
b100000 (
b101100 $
b110 #
b110 '
b110 *
#515000
b1001100 !
b1001100 &
b1000000 (
b1001100 $
b111 #
b111 '
b111 *
#520000
b0 (
b1101 !
b1101 &
b1101 $
b0 #
b0 '
b1101 "
b1101 %
b1101 )
b0 *
#525000
b1100 !
b1100 &
b1 (
b1100 $
b1 #
b1 '
b1 *
#530000
b1111 !
b1111 &
b10 (
b1111 $
b10 #
b10 '
b10 *
#535000
b1001 !
b1001 &
b100 (
b1001 $
b11 #
b11 '
b11 *
#540000
b101 !
b101 &
b1000 (
b101 $
b100 #
b100 '
b100 *
#545000
b11101 !
b11101 &
b10000 (
b11101 $
b101 #
b101 '
b101 *
#550000
b101101 !
b101101 &
b100000 (
b101101 $
b110 #
b110 '
b110 *
#555000
b1001101 !
b1001101 &
b1000000 (
b1001101 $
b111 #
b111 '
b111 *
#560000
b0 (
b1110 !
b1110 &
b1110 $
b0 #
b0 '
b1110 "
b1110 %
b1110 )
b0 *
#565000
b1111 !
b1111 &
b1 (
b1111 $
b1 #
b1 '
b1 *
#570000
b1100 !
b1100 &
b10 (
b1100 $
b10 #
b10 '
b10 *
#575000
b1010 !
b1010 &
b100 (
b1010 $
b11 #
b11 '
b11 *
#580000
b110 !
b110 &
b1000 (
b110 $
b100 #
b100 '
b100 *
#585000
b11110 !
b11110 &
b10000 (
b11110 $
b101 #
b101 '
b101 *
#590000
b101110 !
b101110 &
b100000 (
b101110 $
b110 #
b110 '
b110 *
#595000
b1001110 !
b1001110 &
b1000000 (
b1001110 $
b111 #
b111 '
b111 *
#600000
b0 (
b1111 !
b1111 &
b1111 $
b0 #
b0 '
b1111 "
b1111 %
b1111 )
b0 *
#605000
b1110 !
b1110 &
b1 (
b1110 $
b1 #
b1 '
b1 *
#610000
b1101 !
b1101 &
b10 (
b1101 $
b10 #
b10 '
b10 *
#615000
b1011 !
b1011 &
b100 (
b1011 $
b11 #
b11 '
b11 *
#620000
b111 !
b111 &
b1000 (
b111 $
b100 #
b100 '
b100 *
#625000
b11111 !
b11111 &
b10000 (
b11111 $
b101 #
b101 '
b101 *
#630000
b101111 !
b101111 &
b100000 (
b101111 $
b110 #
b110 '
b110 *
#635000
b1001111 !
b1001111 &
b1000000 (
b1001111 $
b111 #
b111 '
b111 *
#640000
b0 (
b10000 !
b10000 &
b10000 $
b0 #
b0 '
b10000 "
b10000 %
b10000 )
b0 *
#645000
b10001 !
b10001 &
b1 (
b10001 $
b1 #
b1 '
b1 *
#650000
b10010 !
b10010 &
b10 (
b10010 $
b10 #
b10 '
b10 *
#655000
b10100 !
b10100 &
b100 (
b10100 $
b11 #
b11 '
b11 *
#660000
b11000 !
b11000 &
b1000 (
b11000 $
b100 #
b100 '
b100 *
#665000
b0 !
b0 &
b10000 (
b0 $
b101 #
b101 '
b101 *
#670000
b110000 !
b110000 &
b100000 (
b110000 $
b110 #
b110 '
b110 *
#675000
b1010000 !
b1010000 &
b1000000 (
b1010000 $
b111 #
b111 '
b111 *
#680000
b0 (
b10001 !
b10001 &
b10001 $
b0 #
b0 '
b10001 "
b10001 %
b10001 )
b0 *
#685000
b10000 !
b10000 &
b1 (
b10000 $
b1 #
b1 '
b1 *
#690000
b10011 !
b10011 &
b10 (
b10011 $
b10 #
b10 '
b10 *
#695000
b10101 !
b10101 &
b100 (
b10101 $
b11 #
b11 '
b11 *
#700000
b11001 !
b11001 &
b1000 (
b11001 $
b100 #
b100 '
b100 *
#705000
b1 !
b1 &
b10000 (
b1 $
b101 #
b101 '
b101 *
#710000
b110001 !
b110001 &
b100000 (
b110001 $
b110 #
b110 '
b110 *
#715000
b1010001 !
b1010001 &
b1000000 (
b1010001 $
b111 #
b111 '
b111 *
#720000
b0 (
b10010 !
b10010 &
b10010 $
b0 #
b0 '
b10010 "
b10010 %
b10010 )
b0 *
#725000
b10011 !
b10011 &
b1 (
b10011 $
b1 #
b1 '
b1 *
#730000
b10000 !
b10000 &
b10 (
b10000 $
b10 #
b10 '
b10 *
#735000
b10110 !
b10110 &
b100 (
b10110 $
b11 #
b11 '
b11 *
#740000
b11010 !
b11010 &
b1000 (
b11010 $
b100 #
b100 '
b100 *
#745000
b10 !
b10 &
b10000 (
b10 $
b101 #
b101 '
b101 *
#750000
b110010 !
b110010 &
b100000 (
b110010 $
b110 #
b110 '
b110 *
#755000
b1010010 !
b1010010 &
b1000000 (
b1010010 $
b111 #
b111 '
b111 *
#760000
b0 (
b10011 !
b10011 &
b10011 $
b0 #
b0 '
b10011 "
b10011 %
b10011 )
b0 *
#765000
b10010 !
b10010 &
b1 (
b10010 $
b1 #
b1 '
b1 *
#770000
b10001 !
b10001 &
b10 (
b10001 $
b10 #
b10 '
b10 *
#775000
b10111 !
b10111 &
b100 (
b10111 $
b11 #
b11 '
b11 *
#780000
b11011 !
b11011 &
b1000 (
b11011 $
b100 #
b100 '
b100 *
#785000
b11 !
b11 &
b10000 (
b11 $
b101 #
b101 '
b101 *
#790000
b110011 !
b110011 &
b100000 (
b110011 $
b110 #
b110 '
b110 *
#795000
b1010011 !
b1010011 &
b1000000 (
b1010011 $
b111 #
b111 '
b111 *
#800000
b0 (
b10100 !
b10100 &
b10100 $
b0 #
b0 '
b10100 "
b10100 %
b10100 )
b0 *
#805000
b10101 !
b10101 &
b1 (
b10101 $
b1 #
b1 '
b1 *
#810000
b10110 !
b10110 &
b10 (
b10110 $
b10 #
b10 '
b10 *
#815000
b10000 !
b10000 &
b100 (
b10000 $
b11 #
b11 '
b11 *
#820000
b11100 !
b11100 &
b1000 (
b11100 $
b100 #
b100 '
b100 *
#825000
b100 !
b100 &
b10000 (
b100 $
b101 #
b101 '
b101 *
#830000
b110100 !
b110100 &
b100000 (
b110100 $
b110 #
b110 '
b110 *
#835000
b1010100 !
b1010100 &
b1000000 (
b1010100 $
b111 #
b111 '
b111 *
#840000
b0 (
b10101 !
b10101 &
b10101 $
b0 #
b0 '
b10101 "
b10101 %
b10101 )
b0 *
#845000
b10100 !
b10100 &
b1 (
b10100 $
b1 #
b1 '
b1 *
#850000
b10111 !
b10111 &
b10 (
b10111 $
b10 #
b10 '
b10 *
#855000
b10001 !
b10001 &
b100 (
b10001 $
b11 #
b11 '
b11 *
#860000
b11101 !
b11101 &
b1000 (
b11101 $
b100 #
b100 '
b100 *
#865000
b101 !
b101 &
b10000 (
b101 $
b101 #
b101 '
b101 *
#870000
b110101 !
b110101 &
b100000 (
b110101 $
b110 #
b110 '
b110 *
#875000
b1010101 !
b1010101 &
b1000000 (
b1010101 $
b111 #
b111 '
b111 *
#880000
b0 (
b10110 !
b10110 &
b10110 $
b0 #
b0 '
b10110 "
b10110 %
b10110 )
b0 *
#885000
b10111 !
b10111 &
b1 (
b10111 $
b1 #
b1 '
b1 *
#890000
b10100 !
b10100 &
b10 (
b10100 $
b10 #
b10 '
b10 *
#895000
b10010 !
b10010 &
b100 (
b10010 $
b11 #
b11 '
b11 *
#900000
b11110 !
b11110 &
b1000 (
b11110 $
b100 #
b100 '
b100 *
#905000
b110 !
b110 &
b10000 (
b110 $
b101 #
b101 '
b101 *
#910000
b110110 !
b110110 &
b100000 (
b110110 $
b110 #
b110 '
b110 *
#915000
b1010110 !
b1010110 &
b1000000 (
b1010110 $
b111 #
b111 '
b111 *
#920000
b0 (
b10111 !
b10111 &
b10111 $
b0 #
b0 '
b10111 "
b10111 %
b10111 )
b0 *
#925000
b10110 !
b10110 &
b1 (
b10110 $
b1 #
b1 '
b1 *
#930000
b10101 !
b10101 &
b10 (
b10101 $
b10 #
b10 '
b10 *
#935000
b10011 !
b10011 &
b100 (
b10011 $
b11 #
b11 '
b11 *
#940000
b11111 !
b11111 &
b1000 (
b11111 $
b100 #
b100 '
b100 *
#945000
b111 !
b111 &
b10000 (
b111 $
b101 #
b101 '
b101 *
#950000
b110111 !
b110111 &
b100000 (
b110111 $
b110 #
b110 '
b110 *
#955000
b1010111 !
b1010111 &
b1000000 (
b1010111 $
b111 #
b111 '
b111 *
#960000
b0 (
b11000 !
b11000 &
b11000 $
b0 #
b0 '
b11000 "
b11000 %
b11000 )
b0 *
#965000
b11001 !
b11001 &
b1 (
b11001 $
b1 #
b1 '
b1 *
#970000
b11010 !
b11010 &
b10 (
b11010 $
b10 #
b10 '
b10 *
#975000
b11100 !
b11100 &
b100 (
b11100 $
b11 #
b11 '
b11 *
#980000
b10000 !
b10000 &
b1000 (
b10000 $
b100 #
b100 '
b100 *
#985000
b1000 !
b1000 &
b10000 (
b1000 $
b101 #
b101 '
b101 *
#990000
b111000 !
b111000 &
b100000 (
b111000 $
b110 #
b110 '
b110 *
#995000
b1011000 !
b1011000 &
b1000000 (
b1011000 $
b111 #
b111 '
b111 *
#1000000
b0 (
b11001 !
b11001 &
b11001 $
b0 #
b0 '
b11001 "
b11001 %
b11001 )
b0 *
#1005000
b11000 !
b11000 &
b1 (
b11000 $
b1 #
b1 '
b1 *
#1010000
b11011 !
b11011 &
b10 (
b11011 $
b10 #
b10 '
b10 *
#1015000
b11101 !
b11101 &
b100 (
b11101 $
b11 #
b11 '
b11 *
#1020000
b10001 !
b10001 &
b1000 (
b10001 $
b100 #
b100 '
b100 *
#1025000
b1001 !
b1001 &
b10000 (
b1001 $
b101 #
b101 '
b101 *
#1030000
b111001 !
b111001 &
b100000 (
b111001 $
b110 #
b110 '
b110 *
#1035000
b1011001 !
b1011001 &
b1000000 (
b1011001 $
b111 #
b111 '
b111 *
#1040000
b0 (
b11010 !
b11010 &
b11010 $
b0 #
b0 '
b11010 "
b11010 %
b11010 )
b0 *
#1045000
b11011 !
b11011 &
b1 (
b11011 $
b1 #
b1 '
b1 *
#1050000
b11000 !
b11000 &
b10 (
b11000 $
b10 #
b10 '
b10 *
#1055000
b11110 !
b11110 &
b100 (
b11110 $
b11 #
b11 '
b11 *
#1060000
b10010 !
b10010 &
b1000 (
b10010 $
b100 #
b100 '
b100 *
#1065000
b1010 !
b1010 &
b10000 (
b1010 $
b101 #
b101 '
b101 *
#1070000
b111010 !
b111010 &
b100000 (
b111010 $
b110 #
b110 '
b110 *
#1075000
b1011010 !
b1011010 &
b1000000 (
b1011010 $
b111 #
b111 '
b111 *
#1080000
b0 (
b11011 !
b11011 &
b11011 $
b0 #
b0 '
b11011 "
b11011 %
b11011 )
b0 *
#1085000
b11010 !
b11010 &
b1 (
b11010 $
b1 #
b1 '
b1 *
#1090000
b11001 !
b11001 &
b10 (
b11001 $
b10 #
b10 '
b10 *
#1095000
b11111 !
b11111 &
b100 (
b11111 $
b11 #
b11 '
b11 *
#1100000
b10011 !
b10011 &
b1000 (
b10011 $
b100 #
b100 '
b100 *
#1105000
b1011 !
b1011 &
b10000 (
b1011 $
b101 #
b101 '
b101 *
#1110000
b111011 !
b111011 &
b100000 (
b111011 $
b110 #
b110 '
b110 *
#1115000
b1011011 !
b1011011 &
b1000000 (
b1011011 $
b111 #
b111 '
b111 *
#1120000
b0 (
b11100 !
b11100 &
b11100 $
b0 #
b0 '
b11100 "
b11100 %
b11100 )
b0 *
#1125000
b11101 !
b11101 &
b1 (
b11101 $
b1 #
b1 '
b1 *
#1130000
b11110 !
b11110 &
b10 (
b11110 $
b10 #
b10 '
b10 *
#1135000
b11000 !
b11000 &
b100 (
b11000 $
b11 #
b11 '
b11 *
#1140000
b10100 !
b10100 &
b1000 (
b10100 $
b100 #
b100 '
b100 *
#1145000
b1100 !
b1100 &
b10000 (
b1100 $
b101 #
b101 '
b101 *
#1150000
b111100 !
b111100 &
b100000 (
b111100 $
b110 #
b110 '
b110 *
#1155000
b1011100 !
b1011100 &
b1000000 (
b1011100 $
b111 #
b111 '
b111 *
#1160000
b0 (
b11101 !
b11101 &
b11101 $
b0 #
b0 '
b11101 "
b11101 %
b11101 )
b0 *
#1165000
b11100 !
b11100 &
b1 (
b11100 $
b1 #
b1 '
b1 *
#1170000
b11111 !
b11111 &
b10 (
b11111 $
b10 #
b10 '
b10 *
#1175000
b11001 !
b11001 &
b100 (
b11001 $
b11 #
b11 '
b11 *
#1180000
b10101 !
b10101 &
b1000 (
b10101 $
b100 #
b100 '
b100 *
#1185000
b1101 !
b1101 &
b10000 (
b1101 $
b101 #
b101 '
b101 *
#1190000
b111101 !
b111101 &
b100000 (
b111101 $
b110 #
b110 '
b110 *
#1195000
b1011101 !
b1011101 &
b1000000 (
b1011101 $
b111 #
b111 '
b111 *
#1200000
b0 (
b11110 !
b11110 &
b11110 $
b0 #
b0 '
b11110 "
b11110 %
b11110 )
b0 *
#1205000
b11111 !
b11111 &
b1 (
b11111 $
b1 #
b1 '
b1 *
#1210000
b11100 !
b11100 &
b10 (
b11100 $
b10 #
b10 '
b10 *
#1215000
b11010 !
b11010 &
b100 (
b11010 $
b11 #
b11 '
b11 *
#1220000
b10110 !
b10110 &
b1000 (
b10110 $
b100 #
b100 '
b100 *
#1225000
b1110 !
b1110 &
b10000 (
b1110 $
b101 #
b101 '
b101 *
#1230000
b111110 !
b111110 &
b100000 (
b111110 $
b110 #
b110 '
b110 *
#1235000
b1011110 !
b1011110 &
b1000000 (
b1011110 $
b111 #
b111 '
b111 *
#1240000
b0 (
b11111 !
b11111 &
b11111 $
b0 #
b0 '
b11111 "
b11111 %
b11111 )
b0 *
#1245000
b11110 !
b11110 &
b1 (
b11110 $
b1 #
b1 '
b1 *
#1250000
b11101 !
b11101 &
b10 (
b11101 $
b10 #
b10 '
b10 *
#1255000
b11011 !
b11011 &
b100 (
b11011 $
b11 #
b11 '
b11 *
#1260000
b10111 !
b10111 &
b1000 (
b10111 $
b100 #
b100 '
b100 *
#1265000
b1111 !
b1111 &
b10000 (
b1111 $
b101 #
b101 '
b101 *
#1270000
b111111 !
b111111 &
b100000 (
b111111 $
b110 #
b110 '
b110 *
#1275000
b1011111 !
b1011111 &
b1000000 (
b1011111 $
b111 #
b111 '
b111 *
#1280000
b0 (
b100000 !
b100000 &
b100000 $
b0 #
b0 '
b100000 "
b100000 %
b100000 )
b0 *
#1285000
b100001 !
b100001 &
b1 (
b100001 $
b1 #
b1 '
b1 *
#1290000
b100010 !
b100010 &
b10 (
b100010 $
b10 #
b10 '
b10 *
#1295000
b100100 !
b100100 &
b100 (
b100100 $
b11 #
b11 '
b11 *
#1300000
b101000 !
b101000 &
b1000 (
b101000 $
b100 #
b100 '
b100 *
#1305000
b110000 !
b110000 &
b10000 (
b110000 $
b101 #
b101 '
b101 *
#1310000
b0 !
b0 &
b100000 (
b0 $
b110 #
b110 '
b110 *
#1315000
b1100000 !
b1100000 &
b1000000 (
b1100000 $
b111 #
b111 '
b111 *
#1320000
b0 (
b100001 !
b100001 &
b100001 $
b0 #
b0 '
b100001 "
b100001 %
b100001 )
b0 *
#1325000
b100000 !
b100000 &
b1 (
b100000 $
b1 #
b1 '
b1 *
#1330000
b100011 !
b100011 &
b10 (
b100011 $
b10 #
b10 '
b10 *
#1335000
b100101 !
b100101 &
b100 (
b100101 $
b11 #
b11 '
b11 *
#1340000
b101001 !
b101001 &
b1000 (
b101001 $
b100 #
b100 '
b100 *
#1345000
b110001 !
b110001 &
b10000 (
b110001 $
b101 #
b101 '
b101 *
#1350000
b1 !
b1 &
b100000 (
b1 $
b110 #
b110 '
b110 *
#1355000
b1100001 !
b1100001 &
b1000000 (
b1100001 $
b111 #
b111 '
b111 *
#1360000
b0 (
b100010 !
b100010 &
b100010 $
b0 #
b0 '
b100010 "
b100010 %
b100010 )
b0 *
#1365000
b100011 !
b100011 &
b1 (
b100011 $
b1 #
b1 '
b1 *
#1370000
b100000 !
b100000 &
b10 (
b100000 $
b10 #
b10 '
b10 *
#1375000
b100110 !
b100110 &
b100 (
b100110 $
b11 #
b11 '
b11 *
#1380000
b101010 !
b101010 &
b1000 (
b101010 $
b100 #
b100 '
b100 *
#1385000
b110010 !
b110010 &
b10000 (
b110010 $
b101 #
b101 '
b101 *
#1390000
b10 !
b10 &
b100000 (
b10 $
b110 #
b110 '
b110 *
#1395000
b1100010 !
b1100010 &
b1000000 (
b1100010 $
b111 #
b111 '
b111 *
#1400000
b0 (
b100011 !
b100011 &
b100011 $
b0 #
b0 '
b100011 "
b100011 %
b100011 )
b0 *
#1405000
b100010 !
b100010 &
b1 (
b100010 $
b1 #
b1 '
b1 *
#1410000
b100001 !
b100001 &
b10 (
b100001 $
b10 #
b10 '
b10 *
#1415000
b100111 !
b100111 &
b100 (
b100111 $
b11 #
b11 '
b11 *
#1420000
b101011 !
b101011 &
b1000 (
b101011 $
b100 #
b100 '
b100 *
#1425000
b110011 !
b110011 &
b10000 (
b110011 $
b101 #
b101 '
b101 *
#1430000
b11 !
b11 &
b100000 (
b11 $
b110 #
b110 '
b110 *
#1435000
b1100011 !
b1100011 &
b1000000 (
b1100011 $
b111 #
b111 '
b111 *
#1440000
b0 (
b100100 !
b100100 &
b100100 $
b0 #
b0 '
b100100 "
b100100 %
b100100 )
b0 *
#1445000
b100101 !
b100101 &
b1 (
b100101 $
b1 #
b1 '
b1 *
#1450000
b100110 !
b100110 &
b10 (
b100110 $
b10 #
b10 '
b10 *
#1455000
b100000 !
b100000 &
b100 (
b100000 $
b11 #
b11 '
b11 *
#1460000
b101100 !
b101100 &
b1000 (
b101100 $
b100 #
b100 '
b100 *
#1465000
b110100 !
b110100 &
b10000 (
b110100 $
b101 #
b101 '
b101 *
#1470000
b100 !
b100 &
b100000 (
b100 $
b110 #
b110 '
b110 *
#1475000
b1100100 !
b1100100 &
b1000000 (
b1100100 $
b111 #
b111 '
b111 *
#1480000
b0 (
b100101 !
b100101 &
b100101 $
b0 #
b0 '
b100101 "
b100101 %
b100101 )
b0 *
#1485000
b100100 !
b100100 &
b1 (
b100100 $
b1 #
b1 '
b1 *
#1490000
b100111 !
b100111 &
b10 (
b100111 $
b10 #
b10 '
b10 *
#1495000
b100001 !
b100001 &
b100 (
b100001 $
b11 #
b11 '
b11 *
#1500000
b101101 !
b101101 &
b1000 (
b101101 $
b100 #
b100 '
b100 *
#1505000
b110101 !
b110101 &
b10000 (
b110101 $
b101 #
b101 '
b101 *
#1510000
b101 !
b101 &
b100000 (
b101 $
b110 #
b110 '
b110 *
#1515000
b1100101 !
b1100101 &
b1000000 (
b1100101 $
b111 #
b111 '
b111 *
#1520000
b0 (
b100110 !
b100110 &
b100110 $
b0 #
b0 '
b100110 "
b100110 %
b100110 )
b0 *
#1525000
b100111 !
b100111 &
b1 (
b100111 $
b1 #
b1 '
b1 *
#1530000
b100100 !
b100100 &
b10 (
b100100 $
b10 #
b10 '
b10 *
#1535000
b100010 !
b100010 &
b100 (
b100010 $
b11 #
b11 '
b11 *
#1540000
b101110 !
b101110 &
b1000 (
b101110 $
b100 #
b100 '
b100 *
