proyecto_1_transmisor__diseno/src/design/seven_seg.sv
module seven_seg (
    input logic [3:0] datos,
    output logic [6:0] seg
);

    assign seg[6] = (~datos[3] & datos[2] & datos[0]) |
                (~datos[3] & datos[1]) |
                ( datos[3] & ~datos[2] & ~datos[1]) |
                ( datos[3] & ~datos[0]) |
                (~datos[2] & ~datos[0]) |
                ( datos[2] & datos[1]);

    assign seg[5] = (~datos[2] & ~datos[1]) |
            (~datos[2] & ~datos[0]) |
            (~datos[3] & ~datos[1] & ~datos[0]) |
            (~datos[3] &  datos[1] &  datos[0]) |
            ( datos[3] & ~datos[1] &  datos[0]);


    assign seg[4] = (~datos[2] & ~datos[1]) |
             (~datos[2] &  datos[0]) |
             (~datos[1] &  datos[0]) |
             (~datos[3] &  datos[2]) |
             ( datos[3] & ~datos[2]);


    assign seg[3] = (~datos[3] & datos[1] & ~datos[0]) |
                ( datos[3] & ~datos[1]) |
                (~datos[2] & ~datos[1] & ~datos[0]) |
                (~datos[2] &  datos[1] &  datos[0]) |
                ( datos[2] & ~datos[1] &  datos[0]) |
                ( datos[2] &  datos[1] & ~datos[0]);


    assign seg[2] = ( datos[3] & datos[2]) |
                ( datos[3] & datos[1]) |
                (~datos[2] & ~datos[0]) |
                ( datos[1] & ~datos[0]);


    assign seg[1] = (~datos[3] & datos[2] & ~datos[1]) |
                ( datos[3] & ~datos[2]) |
                ( datos[3] & datos[1]) |
                ( datos[2] & ~datos[0]) |
                (~datos[1] & ~datos[0]);


    assign seg[0] = (~datos[3] & datos[2] & ~datos[1]) |
                ( datos[3] & ~datos[2]) |
                ( datos[3] & datos[0]) |
                (~datos[2] & datos[1]) |
                ( datos[1] & ~datos[0]);

endmodule

proyecto_1_transmisor__diseno/src/sim/seven_seg_tb.sv
`timescale 1ns/1ps

module seven_seg_tb;

    logic [3:0] datos;
    logic [6:0] seg;
    logic [6:0] expected;

    // DUT
    seven_seg dut (
        .datos(datos),
        .seg(seg)
    );

    // Modelo esperado
    always_comb begin
        case (datos)
            4'h0: expected = 7'b111_1110;
            4'h1: expected = 7'b011_0000;
            4'h2: expected = 7'b110_1101;
            4'h3: expected = 7'b111_1001;
            4'h4: expected = 7'b011_0011;
            4'h5: expected = 7'b101_1011;
            4'h6: expected = 7'b101_1111;
            4'h7: expected = 7'b111_0000;
            4'h8: expected = 7'b111_1111;
            4'h9: expected = 7'b111_1011;
            4'hA: expected = 7'b111_0111;
            4'hB: expected = 7'b001_1111;
            4'hC: expected = 7'b100_1110;
            4'hD: expected = 7'b011_1101;
            4'hE: expected = 7'b100_1111;
            4'hF: expected = 7'b100_0111;
            default: expected = 7'b000_0000;
        endcase
    end

    initial begin
        $display("INICIO TEST 7-SEG");

        // Probar todos los valores (0 a 15)
        for (int i = 0; i < 16; i++) begin
            datos = i;
            #5;

            if (seg !== expected) begin
                $error("ERROR: datos=%h | seg=%b | esperado=%b",
                        datos, seg, expected);
            end
        end

        $display("TEST COMPLETADO SIN ERRORES");
        $finish;
    end

    initial begin
            $dumpfile("seven_seg_tb.vcd");  // For waveform viewing
            $dumpvars(0, seven_seg_tb);
    end

endmodule

proyecto_1_transmisor__diseno/src/build/seven_seg_tb.vcd
$date
	Tue Apr 07 03:16:23 2026
$end
$version
	Icarus Verilog
$end
$timescale
	1ps
$end
$scope module seven_seg_tb $end
$var wire 7 ! seg [6:0] $end
$var reg 4 " datos [3:0] $end
$var reg 7 # expected [6:0] $end
$scope module dut $end
$var wire 4 $ datos [3:0] $end
$var reg 7 % seg [6:0] $end
$upscope $end
$scope begin $ivl_for_loop0 $end
$var integer 32 & i [31:0] $end
$upscope $end
$upscope $end
$enddefinitions $end
$comment Show the parameter values. $end
$dumpall
$end
#0
$dumpvars
b0 &
b1111110 %
b0 $
b1111110 #
b0 "
b1111110 !
$end
#5000
b110000 !
b110000 %
b110000 #
b1 "
b1 $
b1 &
#10000
b1101101 !
b1101101 %
b1101101 #
b10 "
b10 $
b10 &
#15000
b1111001 !
b1111001 %
b1111001 #
b11 "
b11 $
b11 &
#20000
b110011 !
b110011 %
b110011 #
b100 "
b100 $
b100 &
#25000
b1011011 !
b1011011 %
b1011011 #
b101 "
b101 $
b101 &
#30000
b1011111 !
b1011111 %
b1011111 #
b110 "
b110 $
b110 &
#35000
b1110000 !
b1110000 %
b1110000 #
b111 "
b111 $
b111 &
#40000
b1111111 !
b1111111 %
b1111111 #
b1000 "
b1000 $
b1000 &
#45000
b1111011 !
b1111011 %
b1111011 #
b1001 "
b1001 $
b1001 &
#50000
b1110111 !
b1110111 %
b1110111 #
b1010 "
b1010 $
b1010 &
#55000
b11111 !
b11111 %
b11111 #
b1011 "
b1011 $
b1011 &
#60000
b1001110 !
b1001110 %
b1001110 #
b1100 "
b1100 $
b1100 &
#65000
b111101 !
b111101 %
b111101 #
b1101 "
b1101 $
b1101 &
#70000
b1001111 !
b1001111 %
b1001111 #
b1110 "
b1110 $
b1110 &
#75000
b1000111 !
b1000111 %
b1000111 #
b1111 "
b1111 $
b1111 &
#80000
b10000 &
