proyecto_1_transmisor__diseno/src/design/seven_seg.sv
module seven_seg (
    input logic [3:0] datos,
    output logic [6:0] seg
);

    assign seg[6] = (~datos[3] & datos[2] & datos[0]) |
                (~datos[3] & datos[1]) |
                ( datos[3] & ~datos[2] & ~datos[1]) |
                ( datos[3] & ~datos[0]) |
                (~datos[2] & ~datos[0]) |
                ( datos[2] & datos[1]);

    assign seg[5] = (~datos[2] & ~datos[1]) |
            (~datos[2] & ~datos[0]) |
            (~datos[3] & ~datos[1] & ~datos[0]) |
            (~datos[3] &  datos[1] &  datos[0]) |
            ( datos[3] & ~datos[1] &  datos[0]);


    assign seg[4] = (~datos[2] & ~datos[1]) |
             (~datos[2] &  datos[0]) |
             (~datos[1] &  datos[0]) |
             (~datos[3] &  datos[2]) |
             ( datos[3] & ~datos[2]);


    assign seg[3] = (~datos[3] & datos[1] & ~datos[0]) |
                ( datos[3] & ~datos[1]) |
                (~datos[2] & ~datos[1] & ~datos[0]) |
                (~datos[2] &  datos[1] &  datos[0]) |
                ( datos[2] & ~datos[1] &  datos[0]) |
                ( datos[2] &  datos[1] & ~datos[0]);


    assign seg[2] = ( datos[3] & datos[2]) |
                ( datos[3] & datos[1]) |
                (~datos[2] & ~datos[0]) |
                ( datos[1] & ~datos[0]);


    assign seg[1] = (~datos[3] & datos[2] & ~datos[1]) |
                ( datos[3] & ~datos[2]) |
                ( datos[3] & datos[1]) |
                ( datos[2] & ~datos[0]) |
                (~datos[1] & ~datos[0]);


    assign seg[0] = (~datos[3] & datos[2] & ~datos[1]) |
                ( datos[3] & ~datos[2]) |
                ( datos[3] & datos[0]) |
                (~datos[2] & datos[1]) |
                ( datos[1] & ~datos[0]);

endmodule

proyecto_1_transmisor__diseno/src/design/error_generator.sv
module error_generator (
    input logic [2:0] error_pos,
    input logic [6:0] datos,
    output logic [6:0] datos_error
);

    logic [6:0] mascara;

    assign mascara = (error_pos == 3'b000) ? 7'b0000000:  7'b0000001 << (error_pos-1);

    assign datos_error = datos ^ mascara;

endmodule

proyecto_1_transmisor__diseno/src/design/codification.sv
module codification (
    input logic [3:0] i,
    output logic [6:0] h
);

    logic [2:0] c;

    assign c[0] = i[0] ^ i[1] ^ i[3];
    assign c[1] = i[0] ^ i[2] ^ i[3];
    assign c[2] = i[1] ^ i[2] ^ i[3];

    assign h = {i[3], i[2], i[1], c[2], i[0], c[1], c[0]};


    
endmodule

proyecto_1_transmisor__diseno/src/design/transmitter_top.sv
module transmitter_top (
    input logic [2:0] error_pos,
    input logic [3:0] datos,
    output logic [6:0] hamming_error,
    output logic [6:0] seg
);

    logic [6:0] hamming_correcto;

    codification mod_codificador(
        .i(datos),
        .h(hamming_correcto)
    );

    error_generator mod_error(
        .error_pos(error_pos),
        .datos(hamming_correcto),
        .datos_error(hamming_error)
    );

    seven_seg mod_7seg(
        .datos(datos),
        .seg(seg)
    );

endmodule

proyecto_1_transmisor__diseno/src/sim/transmitter_top_tb.sv
`timescale 1ns/1ps

module transmitter_top_tb;

    logic [2:0] error_pos;
    logic [3:0] datos;
    logic [6:0] hamming_error;
    logic [6:0] seg;

    // Señales internas esperadas
    logic [6:0] hamming_correcto;
    logic [6:0] expected_hamming_error;
    logic [6:0] expected_seg;
    logic [2:0] c;

    // DUT
    transmitter_top dut (
        .error_pos(error_pos),
        .datos(datos),
        .hamming_error(hamming_error),
        .seg(seg)
    );

    // Modelo esperado del codificador (Hamming 7,4)
    always_comb begin
        c[0] = datos[0] ^ datos[1] ^ datos[3];
        c[1] = datos[0] ^ datos[2] ^ datos[3];
        c[2] = datos[1] ^ datos[2] ^ datos[3];

        hamming_correcto = {datos[3], datos[2], datos[1], c[2],
                            datos[0], c[1], c[0]};
    end

    // Modelo esperado del error
    always_comb begin
        if (error_pos == 3'b000)
            expected_hamming_error = hamming_correcto;
        else
            expected_hamming_error = hamming_correcto ^ (7'b1 << (error_pos - 1));
    end

    // Modelo esperado del 7 segmentos
    always_comb begin
        case (datos)
            4'h0: expected_seg = 7'b111_1110;
            4'h1: expected_seg = 7'b011_0000;
            4'h2: expected_seg = 7'b110_1101;
            4'h3: expected_seg = 7'b111_1001;
            4'h4: expected_seg = 7'b011_0011;
            4'h5: expected_seg = 7'b101_1011;
            4'h6: expected_seg = 7'b101_1111;
            4'h7: expected_seg = 7'b111_0000;
            4'h8: expected_seg = 7'b111_1111;
            4'h9: expected_seg = 7'b111_1011;
            4'hA: expected_seg = 7'b111_0111;
            4'hB: expected_seg = 7'b001_1111;
            4'hC: expected_seg = 7'b100_1110;
            4'hD: expected_seg = 7'b011_1101;
            4'hE: expected_seg = 7'b100_1111;
            4'hF: expected_seg = 7'b100_0111;
            default: expected_seg = 7'b000_0000;
        endcase
    end

    initial begin
        $display("INICIO TEST TOP");

        for (int d = 0; d < 16; d++) begin
            datos = d;

            for (int p = 0; p < 8; p++) begin
                error_pos = p;
                #5;

                // Verificar Hamming con error
                if (hamming_error !== expected_hamming_error) begin
                    $error("ERROR HAMMING: datos=%b pos=%0d | salida=%b esperado=%b",
                            datos, error_pos, hamming_error, expected_hamming_error);
                end

                // Verificar 7 segmentos
                if (seg !== expected_seg) begin
                    $error("ERROR 7SEG: datos=%h | seg=%b esperado=%b",
                            datos, seg, expected_seg);
                end

            end
        end

        $display("TEST COMPLETADO SIN ERRORES");
        $finish;
    end

    initial begin
            $dumpfile("transmitter_top_tb.vcd");  // For waveform viewing
            $dumpvars(0, transmitter_top_tb);
    end


endmodule

proyecto_1_transmisor__diseno/src/build/transmitter_top_tb.vcd
$date
	Tue Apr 14 01:57:03 2026
$end
$version
	Icarus Verilog
$end
$timescale
	1ps
$end
$scope module transmitter_top_tb $end
$var wire 7 ! seg [6:0] $end
$var wire 7 " hamming_error [6:0] $end
$var reg 3 # c [2:0] $end
$var reg 4 $ datos [3:0] $end
$var reg 3 % error_pos [2:0] $end
$var reg 7 & expected_hamming_error [6:0] $end
$var reg 7 ' expected_seg [6:0] $end
$var reg 7 ( hamming_correcto [6:0] $end
$scope module dut $end
$var wire 4 ) datos [3:0] $end
$var wire 3 * error_pos [2:0] $end
$var wire 7 + seg [6:0] $end
$var wire 7 , hamming_error [6:0] $end
$var wire 7 - hamming_correcto [6:0] $end
$scope module mod_7seg $end
$var wire 4 . datos [3:0] $end
$var wire 7 / seg [6:0] $end
$upscope $end
$scope module mod_codificador $end
$var wire 4 0 i [3:0] $end
$var wire 7 1 h [6:0] $end
$var wire 3 2 c [2:0] $end
$upscope $end
$scope module mod_error $end
$var wire 7 3 datos [6:0] $end
$var wire 7 4 datos_error [6:0] $end
$var wire 3 5 error_pos [2:0] $end
$var wire 7 6 mascara [6:0] $end
$upscope $end
$upscope $end
$scope begin $ivl_for_loop0 $end
$var integer 32 7 d [31:0] $end
$scope begin $ivl_for_loop1 $end
$var integer 32 8 p [31:0] $end
$upscope $end
$upscope $end
$upscope $end
$enddefinitions $end
$comment Show the parameter values. $end
$dumpall
$end
#0
$dumpvars
b0 8
b0 7
b0 6
b0 5
b0 4
b0 3
b0 2
b0 1
b0 0
b1111110 /
b0 .
b0 -
b0 ,
b1111110 +
b0 *
b0 )
b0 (
b1111110 '
b0 &
b0 %
b0 $
b0 #
b0 "
b1111110 !
$end
#5000
b1 "
b1 ,
b1 4
b1 6
b1 &
b1 %
b1 *
b1 5
b1 8
#10000
b10 "
b10 ,
b10 4
b10 6
b10 &
b10 %
b10 *
b10 5
b10 8
#15000
b100 "
b100 ,
b100 4
b100 6
b100 &
b11 %
b11 *
b11 5
b11 8
#20000
b1000 "
b1000 ,
b1000 4
b1000 6
b1000 &
b100 %
b100 *
b100 5
b100 8
#25000
b10000 "
b10000 ,
b10000 4
b10000 6
b10000 &
b101 %
b101 *
b101 5
b101 8
#30000
b100000 "
b100000 ,
b100000 4
b100000 6
b100000 &
b110 %
b110 *
b110 5
b110 8
#35000
b1000000 "
b1000000 ,
b1000000 4
b1000000 6
b1000000 &
b111 %
b111 *
b111 5
b111 8
#40000
b110000 !
b110000 +
b110000 /
b11 2
b111 "
b111 ,
b111 4
b0 6
b111 &
b111 -
b111 1
b111 3
b111 (
b11 #
b110000 '
b0 %
b0 *
b0 5
b1 $
b1 )
b1 .
b1 0
b1 7
b0 8
#45000
b110 "
b110 ,
b110 4
b1 6
b110 &
b1 %
b1 *
b1 5
b1 8
#50000
b101 "
b101 ,
b101 4
b10 6
b101 &
b10 %
b10 *
b10 5
b10 8
#55000
b11 "
b11 ,
b11 4
b100 6
b11 &
b11 %
b11 *
b11 5
b11 8
#60000
b1111 "
b1111 ,
b1111 4
b1000 6
b1111 &
b100 %
b100 *
b100 5
b100 8
#65000
b10111 "
b10111 ,
b10111 4
b10000 6
b10111 &
b101 %
b101 *
b101 5
b101 8
#70000
b100111 "
b100111 ,
b100111 4
b100000 6
b100111 &
b110 %
b110 *
b110 5
b110 8
#75000
b1000111 "
b1000111 ,
b1000111 4
b1000000 6
b1000111 &
b111 %
b111 *
b111 5
b111 8
#80000
b1101101 !
b1101101 +
b1101101 /
b101 2
b11001 "
b11001 ,
b11001 4
b0 6
b11001 &
b11001 -
b11001 1
b11001 3
b11001 (
b101 #
b1101101 '
b0 %
b0 *
b0 5
b10 $
b10 )
b10 .
b10 0
b10 7
b0 8
#85000
b11000 "
b11000 ,
b11000 4
b1 6
b11000 &
b1 %
b1 *
b1 5
b1 8
#90000
b11011 "
b11011 ,
b11011 4
b10 6
b11011 &
b10 %
b10 *
b10 5
b10 8
#95000
b11101 "
b11101 ,
b11101 4
b100 6
b11101 &
b11 %
b11 *
b11 5
b11 8
#100000
b10001 "
b10001 ,
b10001 4
b1000 6
b10001 &
b100 %
b100 *
b100 5
b100 8
#105000
b1001 "
b1001 ,
b1001 4
b10000 6
b1001 &
b101 %
b101 *
b101 5
b101 8
#110000
b111001 "
b111001 ,
b111001 4
b100000 6
b111001 &
b110 %
b110 *
b110 5
b110 8
#115000
b1011001 "
b1011001 ,
b1011001 4
b1000000 6
b1011001 &
b111 %
b111 *
b111 5
b111 8
#120000
b1111001 !
b1111001 +
b1111001 /
b110 2
b11110 "
b11110 ,
b11110 4
b0 6
b11110 &
b11110 -
b11110 1
b11110 3
b11110 (
b110 #
b1111001 '
b0 %
b0 *
b0 5
b11 $
b11 )
b11 .
b11 0
b11 7
b0 8
#125000
b11111 "
b11111 ,
b11111 4
b1 6
b11111 &
b1 %
b1 *
b1 5
b1 8
#130000
b11100 "
b11100 ,
b11100 4
b10 6
b11100 &
b10 %
b10 *
b10 5
b10 8
#135000
b11010 "
b11010 ,
b11010 4
b100 6
b11010 &
b11 %
b11 *
b11 5
b11 8
#140000
b10110 "
b10110 ,
b10110 4
b1000 6
b10110 &
b100 %
b100 *
b100 5
b100 8
#145000
b1110 "
b1110 ,
b1110 4
b10000 6
b1110 &
b101 %
b101 *
b101 5
b101 8
#150000
b111110 "
b111110 ,
b111110 4
b100000 6
b111110 &
b110 %
b110 *
b110 5
b110 8
#155000
b1011110 "
b1011110 ,
b1011110 4
b1000000 6
b1011110 &
b111 %
b111 *
b111 5
b111 8
#160000
b110011 !
b110011 +
b110011 /
b101010 "
b101010 ,
b101010 4
b0 6
b101010 &
b101010 -
b101010 1
b101010 3
b101010 (
b110011 '
b0 %
b0 *
b0 5
b100 $
b100 )
b100 .
b100 0
b100 7
b0 8
#165000
b101011 "
b101011 ,
b101011 4
b1 6
b101011 &
b1 %
b1 *
b1 5
b1 8
#170000
b101000 "
b101000 ,
b101000 4
b10 6
b101000 &
b10 %
b10 *
b10 5
b10 8
#175000
b101110 "
b101110 ,
b101110 4
b100 6
b101110 &
b11 %
b11 *
b11 5
b11 8
#180000
b100010 "
b100010 ,
b100010 4
b1000 6
b100010 &
b100 %
b100 *
b100 5
b100 8
#185000
b111010 "
b111010 ,
b111010 4
b10000 6
b111010 &
b101 %
b101 *
b101 5
b101 8
#190000
b1010 "
b1010 ,
b1010 4
b100000 6
b1010 &
b110 %
b110 *
b110 5
b110 8
#195000
b1101010 "
b1101010 ,
b1101010 4
b1000000 6
b1101010 &
b111 %
b111 *
b111 5
b111 8
#200000
b1011011 !
b1011011 +
b1011011 /
b101 2
b101101 "
b101101 ,
b101101 4
b0 6
b101101 &
b101101 -
b101101 1
b101101 3
b101101 (
b101 #
b1011011 '
b0 %
b0 *
b0 5
b101 $
b101 )
b101 .
b101 0
b101 7
b0 8
#205000
b101100 "
b101100 ,
b101100 4
b1 6
b101100 &
b1 %
b1 *
b1 5
b1 8
#210000
b101111 "
b101111 ,
b101111 4
b10 6
b101111 &
b10 %
b10 *
b10 5
b10 8
#215000
b101001 "
b101001 ,
b101001 4
b100 6
b101001 &
b11 %
b11 *
b11 5
b11 8
#220000
b100101 "
b100101 ,
b100101 4
b1000 6
b100101 &
b100 %
b100 *
b100 5
b100 8
#225000
b111101 "
b111101 ,
b111101 4
b10000 6
b111101 &
b101 %
b101 *
b101 5
b101 8
#230000
b1101 "
b1101 ,
b1101 4
b100000 6
b1101 &
b110 %
b110 *
b110 5
b110 8
#235000
b1101101 "
b1101101 ,
b1101101 4
b1000000 6
b1101101 &
b111 %
b111 *
b111 5
b111 8
#240000
b1011111 !
b1011111 +
b1011111 /
b11 2
b110011 "
b110011 ,
b110011 4
b0 6
b110011 &
b110011 -
b110011 1
b110011 3
b110011 (
b11 #
b1011111 '
b0 %
b0 *
b0 5
b110 $
b110 )
b110 .
b110 0
b110 7
b0 8
#245000
b110010 "
b110010 ,
b110010 4
b1 6
b110010 &
b1 %
b1 *
b1 5
b1 8
#250000
b110001 "
b110001 ,
b110001 4
b10 6
b110001 &
b10 %
b10 *
b10 5
b10 8
#255000
b110111 "
b110111 ,
b110111 4
b100 6
b110111 &
b11 %
b11 *
b11 5
b11 8
#260000
b111011 "
b111011 ,
b111011 4
b1000 6
b111011 &
b100 %
b100 *
b100 5
b100 8
#265000
b100011 "
b100011 ,
b100011 4
b10000 6
b100011 &
b101 %
b101 *
b101 5
b101 8
#270000
b10011 "
b10011 ,
b10011 4
b100000 6
b10011 &
b110 %
b110 *
b110 5
b110 8
#275000
b1110011 "
b1110011 ,
b1110011 4
b1000000 6
b1110011 &
b111 %
b111 *
b111 5
b111 8
#280000
b1110000 !
b1110000 +
b1110000 /
b0 2
b110100 "
b110100 ,
b110100 4
b0 6
b110100 &
b110100 -
b110100 1
b110100 3
b110100 (
b0 #
b1110000 '
b0 %
b0 *
b0 5
b111 $
b111 )
b111 .
b111 0
b111 7
b0 8
#285000
b110101 "
b110101 ,
b110101 4
b1 6
b110101 &
b1 %
b1 *
b1 5
b1 8
#290000
b110110 "
b110110 ,
b110110 4
b10 6
b110110 &
b10 %
b10 *
b10 5
b10 8
#295000
b110000 "
b110000 ,
b110000 4
b100 6
b110000 &
b11 %
b11 *
b11 5
b11 8
#300000
b111100 "
b111100 ,
b111100 4
b1000 6
b111100 &
b100 %
b100 *
b100 5
b100 8
#305000
b100100 "
b100100 ,
b100100 4
b10000 6
b100100 &
b101 %
b101 *
b101 5
b101 8
#310000
b10100 "
b10100 ,
b10100 4
b100000 6
b10100 &
b110 %
b110 *
b110 5
b110 8
#315000
b1110100 "
b1110100 ,
b1110100 4
b1000000 6
b1110100 &
b111 %
b111 *
b111 5
b111 8
#320000
b1111111 !
b1111111 +
b1111111 /
b111 2
b1001011 "
b1001011 ,
b1001011 4
b0 6
b1001011 &
b1001011 -
b1001011 1
b1001011 3
b1001011 (
b111 #
b1111111 '
b0 %
b0 *
b0 5
b1000 $
b1000 )
b1000 .
b1000 0
b1000 7
b0 8
#325000
b1001010 "
b1001010 ,
b1001010 4
b1 6
b1001010 &
b1 %
b1 *
b1 5
b1 8
#330000
b1001001 "
b1001001 ,
b1001001 4
b10 6
b1001001 &
b10 %
b10 *
b10 5
b10 8
#335000
b1001111 "
b1001111 ,
b1001111 4
b100 6
b1001111 &
b11 %
b11 *
b11 5
b11 8
#340000
b1000011 "
b1000011 ,
b1000011 4
b1000 6
b1000011 &
b100 %
b100 *
b100 5
b100 8
#345000
b1011011 "
b1011011 ,
b1011011 4
b10000 6
b1011011 &
b101 %
b101 *
b101 5
b101 8
#350000
b1101011 "
b1101011 ,
b1101011 4
b100000 6
b1101011 &
b110 %
b110 *
b110 5
b110 8
#355000
b1011 "
b1011 ,
b1011 4
b1000000 6
b1011 &
b111 %
b111 *
b111 5
b111 8
#360000
b1111011 !
b1111011 +
b1111011 /
b100 2
b1001100 "
b1001100 ,
b1001100 4
b0 6
b1001100 &
b1001100 -
b1001100 1
b1001100 3
b1001100 (
b100 #
b1111011 '
b0 %
b0 *
b0 5
b1001 $
b1001 )
b1001 .
b1001 0
b1001 7
b0 8
#365000
b1001101 "
b1001101 ,
b1001101 4
b1 6
b1001101 &
b1 %
b1 *
b1 5
b1 8
#370000
b1001110 "
b1001110 ,
b1001110 4
b10 6
b1001110 &
b10 %
b10 *
b10 5
b10 8
#375000
b1001000 "
b1001000 ,
b1001000 4
b100 6
b1001000 &
b11 %
b11 *
b11 5
b11 8
#380000
b1000100 "
b1000100 ,
b1000100 4
b1000 6
b1000100 &
b100 %
b100 *
b100 5
b100 8
#385000
b1011100 "
b1011100 ,
b1011100 4
b10000 6
b1011100 &
b101 %
b101 *
b101 5
b101 8
#390000
b1101100 "
b1101100 ,
b1101100 4
b100000 6
b1101100 &
b110 %
b110 *
b110 5
b110 8
#395000
b1100 "
b1100 ,
b1100 4
b1000000 6
b1100 &
b111 %
b111 *
b111 5
b111 8
#400000
b1110111 !
b1110111 +
b1110111 /
b10 2
b1010010 "
b1010010 ,
b1010010 4
b0 6
b1010010 &
b1010010 -
b1010010 1
b1010010 3
b1010010 (
b10 #
b1110111 '
b0 %
b0 *
b0 5
b1010 $
b1010 )
b1010 .
b1010 0
b1010 7
b0 8
#405000
b1010011 "
b1010011 ,
b1010011 4
b1 6
b1010011 &
b1 %
b1 *
b1 5
b1 8
#410000
b1010000 "
b1010000 ,
b1010000 4
b10 6
b1010000 &
b10 %
b10 *
b10 5
b10 8
#415000
b1010110 "
b1010110 ,
b1010110 4
b100 6
b1010110 &
b11 %
b11 *
b11 5
b11 8
#420000
b1011010 "
b1011010 ,
b1011010 4
b1000 6
b1011010 &
b100 %
b100 *
b100 5
b100 8
#425000
b1000010 "
b1000010 ,
b1000010 4
b10000 6
b1000010 &
b101 %
b101 *
b101 5
b101 8
#430000
b1110010 "
b1110010 ,
b1110010 4
b100000 6
b1110010 &
b110 %
b110 *
b110 5
b110 8
#435000
b10010 "
b10010 ,
b10010 4
b1000000 6
b10010 &
b111 %
b111 *
b111 5
b111 8
#440000
b11111 !
b11111 +
b11111 /
b1 2
b1010101 "
b1010101 ,
b1010101 4
b0 6
b1010101 &
b1010101 -
b1010101 1
b1010101 3
b1010101 (
b1 #
b11111 '
b0 %
b0 *
b0 5
b1011 $
b1011 )
b1011 .
b1011 0
b1011 7
b0 8
#445000
b1010100 "
b1010100 ,
b1010100 4
b1 6
b1010100 &
b1 %
b1 *
b1 5
b1 8
#450000
b1010111 "
b1010111 ,
b1010111 4
b10 6
b1010111 &
b10 %
b10 *
b10 5
b10 8
#455000
b1010001 "
b1010001 ,
b1010001 4
b100 6
b1010001 &
b11 %
b11 *
b11 5
b11 8
#460000
b1011101 "
b1011101 ,
b1011101 4
b1000 6
b1011101 &
b100 %
b100 *
b100 5
b100 8
#465000
b1000101 "
b1000101 ,
b1000101 4
b10000 6
b1000101 &
b101 %
b101 *
b101 5
b101 8
#470000
b1110101 "
b1110101 ,
b1110101 4
b100000 6
b1110101 &
b110 %
b110 *
b110 5
b110 8
#475000
b10101 "
b10101 ,
b10101 4
b1000000 6
b10101 &
b111 %
b111 *
b111 5
b111 8
#480000
b1001110 !
b1001110 +
b1001110 /
b1100001 "
b1100001 ,
b1100001 4
b0 6
b1100001 &
b1100001 -
b1100001 1
b1100001 3
b1100001 (
b1001110 '
b0 %
b0 *
b0 5
b1100 $
b1100 )
b1100 .
b1100 0
b1100 7
b0 8
#485000
b1100000 "
b1100000 ,
b1100000 4
b1 6
b1100000 &
b1 %
b1 *
b1 5
b1 8
#490000
b1100011 "
b1100011 ,
b1100011 4
b10 6
b1100011 &
b10 %
b10 *
b10 5
b10 8
#495000
b1100101 "
b1100101 ,
b1100101 4
b100 6
b1100101 &
b11 %
b11 *
b11 5
b11 8
#500000
b1101001 "
b1101001 ,
b1101001 4
b1000 6
b1101001 &
b100 %
b100 *
b100 5
b100 8
#505000
b1110001 "
b1110001 ,
b1110001 4
b10000 6
b1110001 &
b101 %
b101 *
b101 5
b101 8
#510000
b1000001 "
b1000001 ,
b1000001 4
b100000 6
b1000001 &
b110 %
b110 *
b110 5
b110 8
#515000
b100001 "
b100001 ,
b100001 4
b1000000 6
b100001 &
b111 %
b111 *
b111 5
b111 8
#520000
b111101 !
b111101 +
b111101 /
b10 2
b1100110 "
b1100110 ,
b1100110 4
b0 6
b1100110 &
b1100110 -
b1100110 1
b1100110 3
b1100110 (
b10 #
b111101 '
b0 %
b0 *
b0 5
b1101 $
b1101 )
b1101 .
b1101 0
b1101 7
b0 8
#525000
b1100111 "
b1100111 ,
b1100111 4
b1 6
b1100111 &
b1 %
b1 *
b1 5
b1 8
#530000
b1100100 "
b1100100 ,
b1100100 4
b10 6
b1100100 &
b10 %
b10 *
b10 5
b10 8
#535000
b1100010 "
b1100010 ,
b1100010 4
b100 6
b1100010 &
b11 %
b11 *
b11 5
b11 8
#540000
b1101110 "
b1101110 ,
b1101110 4
b1000 6
b1101110 &
b100 %
b100 *
b100 5
b100 8
#545000
b1110110 "
b1110110 ,
b1110110 4
b10000 6
b1110110 &
b101 %
b101 *
b101 5
b101 8
#550000
b1000110 "
b1000110 ,
b1000110 4
b100000 6
b1000110 &
b110 %
b110 *
b110 5
b110 8
#555000
b100110 "
b100110 ,
b100110 4
b1000000 6
b100110 &
b111 %
b111 *
b111 5
b111 8
#560000
b1001111 !
b1001111 +
b1001111 /
b100 2
b1111000 "
b1111000 ,
b1111000 4
b0 6
b1111000 &
b1111000 -
b1111000 1
b1111000 3
b1111000 (
b100 #
b1001111 '
b0 %
b0 *
b0 5
b1110 $
b1110 )
b1110 .
b1110 0
b1110 7
b0 8
#565000
b1111001 "
b1111001 ,
b1111001 4
b1 6
b1111001 &
b1 %
b1 *
b1 5
b1 8
#570000
b1111010 "
b1111010 ,
b1111010 4
b10 6
b1111010 &
b10 %
b10 *
b10 5
b10 8
#575000
b1111100 "
b1111100 ,
b1111100 4
b100 6
b1111100 &
b11 %
b11 *
b11 5
b11 8
#580000
b1110000 "
b1110000 ,
b1110000 4
b1000 6
b1110000 &
b100 %
b100 *
b100 5
b100 8
#585000
b1101000 "
b1101000 ,
b1101000 4
b10000 6
b1101000 &
b101 %
b101 *
b101 5
b101 8
#590000
b1011000 "
b1011000 ,
b1011000 4
b100000 6
b1011000 &
b110 %
b110 *
b110 5
b110 8
#595000
b111000 "
b111000 ,
b111000 4
b1000000 6
b111000 &
b111 %
b111 *
b111 5
b111 8
#600000
b1000111 !
b1000111 +
b1000111 /
b111 2
b1111111 "
b1111111 ,
b1111111 4
b0 6
b1111111 &
b1111111 -
b1111111 1
b1111111 3
b1111111 (
b111 #
b1000111 '
b0 %
b0 *
b0 5
b1111 $
b1111 )
b1111 .
b1111 0
b1111 7
b0 8
#605000
b1111110 "
b1111110 ,
b1111110 4
b1 6
b1111110 &
b1 %
b1 *
b1 5
b1 8
#610000
b1111101 "
b1111101 ,
b1111101 4
b10 6
b1111101 &
b10 %
b10 *
b10 5
b10 8
#615000
b1111011 "
b1111011 ,
b1111011 4
b100 6
b1111011 &
b11 %
b11 *
b11 5
b11 8
#620000
b1110111 "
b1110111 ,
b1110111 4
b1000 6
b1110111 &
b100 %
b100 *
b100 5
b100 8
#625000
b1101111 "
b1101111 ,
b1101111 4
b10000 6
b1101111 &
b101 %
b101 *
b101 5
b101 8
#630000
b1011111 "
b1011111 ,
b1011111 4
b100000 6
b1011111 &
b110 %
b110 *
b110 5
b110 8
#635000
b111111 "
b111111 ,
b111111 4
b1000000 6
b111111 &
b111 %
b111 *
b111 5
b111 8
#640000
b10000 7
b1000 8
